{
  "char_to_id": {
    "<PAD>": 0,
    "<UNK>": 1,
    "<BOS>": 2,
    "<EOS>": 3,
    "\n": 4,
    " ": 5,
    ",": 6,
    "-": 7,
    ".": 8,
    "/": 9,
    "0": 10,
    "1": 11,
    "2": 12,
    "3": 13,
    "4": 14,
    "5": 15,
    ":": 16,
    "A": 17,
    "B": 18,
    "C": 19,
    "F": 20,
    "H": 21,
    "I": 22,
    "R": 23,
    "S": 24,
    "T": 25,
    "U": 26,
    "Y": 27,
    "a": 28,
    "b": 29,
    "d": 30,
    "e": 31,
    "g": 32,
    "h": 33,
    "i": 34,
    "k": 35,
    "l": 36,
    "m": 37,
    "n": 38,
    "o": 39,
    "r": 40,
    "s": 41,
    "t": 42,
    "u": 43,
    "v": 44,
    "w": 45,
    "y": 46,
    "~": 47,
    "В": 48,
    "Г": 49,
    "Д": 50,
    "И": 51,
    "К": 52,
    "М": 53,
    "Н": 54,
    "П": 55,
    "Р": 56,
    "С": 57,
    "У": 58,
    "Ф": 59,
    "Ц": 60,
    "Э": 61,
    "а": 62,
    "б": 63,
    "в": 64,
    "г": 65,
    "д": 66,
    "е": 67,
    "ж": 68,
    "з": 69,
    "и": 70,
    "й": 71,
    "к": 72,
    "л": 73,
    "м": 74,
    "н": 75,
    "о": 76,
    "п": 77,
    "р": 78,
    "с": 79,
    "т": 80,
    "у": 81,
    "ф": 82,
    "х": 83,
    "ц": 84,
    "ч": 85,
    "ш": 86,
    "щ": 87,
    "ы": 88,
    "ь": 89,
    "э": 90,
    "ю": 91,
    "я": 92,
    "ё": 93,
    "—": 94,
    "→": 95
  },
  "vocab_size": 96
}